{
  "Strecken": [
    {
      "ZID": 60,
      "SID": 12208,
      "STID": 786,
      "Sportart": 34,
      "Streckenname": "1,7 km Trainingsstrecke",
      "Laenge": 1732,
      "TC": 45,
      "HD": 24,
      "Schwierigkeitsgrad": 37,
      "LL_Technik": 40,
      "s_cmp": "1,7 km trainingsstrecke",
      "kats": [1],
      "trackstatus": 1,
      "rowpos": 1
    },
    {
      "ZID": 117,
      "SID": 685,
      "STID": 145,
      "Sportart": 34,
      "Streckenname": "1200 Meter Strecke",
      "Laenge": 1200,
      "TC": 16,
      "HD": 11,
      "Schwierigkeitsgrad": 37,
      "LL_Technik": 40,
      "s_cmp": "1200 meter strecke",
      "kats": [],
      "trackstatus": 1,
      "rowpos": 2
    },
    {
      "ZID": 60,
      "SID": 1075,
      "STID": 786,
      "Sportart": 34,
      "Streckenname": "2,5 km Rothaus Runde",
      "Laenge": 2464,
      "TC": 93,
      "HD": 39,
      "Schwierigkeitsgrad": 38,
      "LL_Technik": 40,
      "s_cmp": "2,5 km rothaus runde",
      "kats": [5, 6, 7],
      "trackstatus": 1,
      "rowpos": 3
    },
    {
      "ZID": 60,
      "SID": 12210,
      "STID": 786,
      "Sportart": 34,
      "Streckenname": "2,5 km Trainingsstrecke",
      "Laenge": 2508,
      "TC": 81,
      "HD": 29,
      "Schwierigkeitsgrad": 37,
      "LL_Technik": 40,
      "s_cmp": "2,5 km trainingsstrecke",
      "kats": [1],
      "trackstatus": 1,
      "rowpos": 4
    },
    {
      "ZID": 60,
      "SID": 1076,
      "STID": 786,
      "Sportart": 34,
      "Streckenname": "3,3 km Wettkampfstrecke",
      "Laenge": 3268,
      "TC": 127,
      "HD": 47,
      "Schwierigkeitsgrad": 39,
      "LL_Technik": 40,
      "s_cmp": "3,3 km wettkampfstrecke",
      "kats": [],
      "trackstatus": 1,
      "rowpos": 5
    },
    {
      "ZID": 60,
      "SID": 1077,
      "STID": 786,
      "Sportart": 34,
      "Streckenname": "3,75 km Wettkampfstrecke",
      "Laenge": 3584,
      "TC": 137,
      "HD": 47,
      "Schwierigkeitsgrad": 39,
      "LL_Technik": 40,
      "s_cmp": "3,75 km wettkampfstrecke",
      "kats": [],
      "trackstatus": 1,
      "rowpos": 6
    },
    {
      "ZID": 39,
      "SID": 692,
      "STID": 159,
      "Sportart": 34,
      "Streckenname": "Adlerwald - Loipe",
      "Laenge": 2500,
      "TC": 90,
      "HD": 45,
      "Schwierigkeitsgrad": 39,
      "LL_Technik": 40,
      "s_cmp": "adlerwald - loipe",
      "kats": [5, 7],
      "trackstatus": 1,
      "rowpos": 7
    },
    {
      "ZID": 126,
      "SID": 729,
      "STID": 127,
      "Sportart": 34,
      "Streckenname": "Balzhauser Loipe",
      "Laenge": 5500,
      "TC": 114,
      "HD": 54,
      "Schwierigkeitsgrad": 38,
      "LL_Technik": 41,
      "s_cmp": "balzhauser loipe",
      "kats": [],
      "trackstatus": 1,
      "rowpos": 8
    },
    {
      "ZID": 139,
      "SID": 717,
      "STID": 118,
      "Sportart": 34,
      "Streckenname": "Bergle Loipe",
      "Laenge": 3100,
      "TC": 79,
      "HD": 66,
      "Schwierigkeitsgrad": 38,
      "LL_Technik": 40,
      "s_cmp": "bergle loipe",
      "kats": [],
      "trackstatus": 0,
      "rowpos": 9
    },
    {
      "ZID": 126,
      "SID": 726,
      "STID": 113,
      "Sportart": 34,
      "Streckenname": "Bergwiesen Loipe",
      "Laenge": 3100,
      "TC": 34,
      "HD": 30,
      "Schwierigkeitsgrad": 37,
      "LL_Technik": 41,
      "s_cmp": "bergwiesen loipe",
      "kats": [1],
      "trackstatus": 1,
      "rowpos": 10
    },
    {
      "ZID": 126,
      "SID": 732,
      "STID": 108,
      "Sportart": 34,
      "Streckenname": "Bildhaus Bergloipe",
      "Laenge": 2400,
      "TC": 35,
      "HD": 15,
      "Schwierigkeitsgrad": 38,
      "LL_Technik": 41,
      "s_cmp": "bildhaus bergloipe",
      "kats": [],
      "trackstatus": 1,
      "rowpos": 11
    },
    {
      "ZID": 126,
      "SID": 734,
      "STID": 108,
      "Sportart": 34,
      "Streckenname": "Bildhaus Bergloipe",
      "Laenge": 7000,
      "TC": 144,
      "HD": 92,
      "Schwierigkeitsgrad": 39,
      "LL_Technik": 41,
      "s_cmp": "bildhaus bergloipe",
      "kats": [],
      "trackstatus": 1,
      "rowpos": 12
    },
    {
      "ZID": 126,
      "SID": 733,
      "STID": 105,
      "Sportart": 34,
      "Streckenname": "Bildstöckle Loipe",
      "Laenge": 3300,
      "TC": 86,
      "HD": 79,
      "Schwierigkeitsgrad": 39,
      "LL_Technik": 41,
      "s_cmp": "bildstockle loipe",
      "kats": [],
      "trackstatus": 1,
      "rowpos": 13
    },
    {
      "ZID": 205,
      "SID": 1055,
      "STID": 185,
      "Sportart": 34,
      "Streckenname": "Blaue Strecke",
      "Laenge": 3100,
      "TC": 67,
      "HD": 47,
      "Schwierigkeitsgrad": 37,
      "LL_Technik": 40,
      "s_cmp": "blaue strecke",
      "kats": [1],
      "trackstatus": 1,
      "rowpos": 14
    },
    {
      "ZID": 126,
      "SID": 730,
      "STID": 122,
      "Sportart": 34,
      "Streckenname": "Bohlisch Loipe",
      "Laenge": 2500,
      "TC": 30,
      "HD": 22,
      "Schwierigkeitsgrad": 38,
      "LL_Technik": 40,
      "s_cmp": "bohlisch loipe",
      "kats": [],
      "trackstatus": 0,
      "rowpos": 15
    },
    {
      "ZID": 162,
      "SID": 1071,
      "STID": 197,
      "Sportart": 34,
      "Streckenname": "Bregnitzhof Loipe",
      "Laenge": 9900,
      "TC": 118,
      "HD": 63,
      "Schwierigkeitsgrad": 38,
      "LL_Technik": 42,
      "s_cmp": "bregnitzhof loipe",
      "kats": [],
      "trackstatus": 0,
      "rowpos": 16
    },
    {
      "ZID": 143,
      "SID": 3027,
      "STID": 799,
      "Sportart": 34,
      "Streckenname": "Bregtalloipe",
      "Laenge": 2927,
      "TC": "",
      "HD": "",
      "Schwierigkeitsgrad": 40,
      "LL_Technik": 41,
      "s_cmp": "bregtalloipe",
      "kats": [],
      "trackstatus": 1,
      "rowpos": 17
    },
    {
      "ZID": 178,
      "SID": 769,
      "STID": 192,
      "Sportart": 34,
      "Streckenname": "Brigachloipe",
      "Laenge": 12900,
      "TC": 310,
      "HD": 200,
      "Schwierigkeitsgrad": 39,
      "LL_Technik": 41,
      "s_cmp": "brigachloipe",
      "kats": [3],
      "trackstatus": 1,
      "rowpos": 18
    },
    {
      "ZID": 162,
      "SID": 1072,
      "STID": 197,
      "Sportart": 34,
      "Streckenname": "Buchenberg Loipe",
      "Laenge": 8300,
      "TC": 138,
      "HD": 90,
      "Schwierigkeitsgrad": 39,
      "LL_Technik": 41,
      "s_cmp": "buchenberg loipe",
      "kats": [],
      "trackstatus": 0,
      "rowpos": 19
    },
    {
      "ZID": 42,
      "SID": 673,
      "STID": 101,
      "Sportart": 34,
      "Streckenname": "Bühl Loipe",
      "Laenge": 3700,
      "TC": 61,
      "HD": 47,
      "Schwierigkeitsgrad": 37,
      "LL_Technik": 40,
      "s_cmp": "buhl loipe",
      "kats": [1],
      "trackstatus": 1,
      "rowpos": 20
    },
    {
      "ZID": 126,
      "SID": 728,
      "STID": 113,
      "Sportart": 34,
      "Streckenname": "Bühl Loipe (Birkendorf)",
      "Laenge": 7300,
      "TC": 81,
      "HD": 49,
      "Schwierigkeitsgrad": 38,
      "LL_Technik": 41,
      "s_cmp": "buhl loipe (birkendorf)",
      "kats": [2],
      "trackstatus": 1,
      "rowpos": 21
    },
    {
      "ZID": 126,
      "SID": 727,
      "STID": 104,
      "Sportart": 34,
      "Streckenname": "Bühl Loipe (Ühlingen)",
      "Laenge": 3200,
      "TC": 82,
      "HD": 78,
      "Schwierigkeitsgrad": 38,
      "LL_Technik": 41,
      "s_cmp": "buhl loipe (uhlingen)",
      "kats": [],
      "trackstatus": 1,
      "rowpos": 22
    },
    {
      "ZID": 41,
      "SID": 703,
      "STID": 133,
      "Sportart": 34,
      "Streckenname": "Drescherspur",
      "Laenge": 1400,
      "TC": 26,
      "HD": 22,
      "Schwierigkeitsgrad": 37,
      "LL_Technik": 40,
      "s_cmp": "drescherspur",
      "kats": [1],
      "trackstatus": 1,
      "rowpos": 23
    },
    {
      "ZID": 68,
      "SID": 740,
      "STID": 135,
      "Sportart": 34,
      "Streckenname": "Dresselbach - Spur",
      "Laenge": 4100,
      "TC": 95,
      "HD": 48,
      "Schwierigkeitsgrad": 38,
      "LL_Technik": 40,
      "s_cmp": "dresselbach - spur",
      "kats": [],
      "trackstatus": 1,
      "rowpos": 24
    },
    {
      "ZID": 139,
      "SID": 719,
      "STID": 121,
      "Sportart": 34,
      "Streckenname": "Egerten Loipe",
      "Laenge": 9600,
      "TC": 172,
      "HD": 124,
      "Schwierigkeitsgrad": 38,
      "LL_Technik": 40,
      "s_cmp": "egerten loipe",
      "kats": [],
      "trackstatus": 0,
      "rowpos": 25
    },
    {
      "ZID": 162,
      "SID": 1070,
      "STID": 196,
      "Sportart": 34,
      "Streckenname": "Enzianwiese Klassisch",
      "Laenge": 6600,
      "TC": 92,
      "HD": 31,
      "Schwierigkeitsgrad": 38,
      "LL_Technik": 41,
      "s_cmp": "enzianwiese klassisch",
      "kats": [2],
      "trackstatus": 0,
      "rowpos": 26
    },
    {
      "ZID": 162,
      "SID": 1069,
      "STID": 196,
      "Sportart": 34,
      "Streckenname": "Enzianwiese Skating",
      "Laenge": 5100,
      "TC": 54,
      "HD": 34,
      "Schwierigkeitsgrad": 37,
      "LL_Technik": 42,
      "s_cmp": "enzianwiese skating",
      "kats": [],
      "trackstatus": 0,
      "rowpos": 27
    },
    {
      "ZID": 42,
      "SID": 676,
      "STID": 101,
      "Sportart": 34,
      "Streckenname": "Erlenberg Loipe",
      "Laenge": 7500,
      "TC": 184,
      "HD": 96,
      "Schwierigkeitsgrad": 38,
      "LL_Technik": 41,
      "s_cmp": "erlenberg loipe",
      "kats": [],
      "trackstatus": 1,
      "rowpos": 28
    },
    {
      "ZID": 177,
      "SID": 754,
      "STID": 189,
      "Sportart": 34,
      "Streckenname": "Farnbergloipe",
      "Laenge": 9400,
      "TC": 230,
      "HD": 69,
      "Schwierigkeitsgrad": 38,
      "LL_Technik": 41,
      "s_cmp": "farnbergloipe",
      "kats": [2],
      "trackstatus": 1,
      "rowpos": 29
    },
    {
      "ZID": 39,
      "SID": 697,
      "STID": 162,
      "Sportart": 34,
      "Streckenname": "Fernskiwanderweg Hinterzarten - Schluchsee",
      "Laenge": 30000,
      "TC": "",
      "HD": "",
      "Schwierigkeitsgrad": 39,
      "LL_Technik": 41,
      "s_cmp": "fernskiwanderweg hinterzarten - schluchsee",
      "kats": [],
      "trackstatus": 1,
      "rowpos": 30
    },
    {
      "ZID": 176,
      "SID": 2000,
      "STID": 813,
      "Sportart": 34,
      "Streckenname": "Fernskiwanderweg Schonach - Belchen Etappe 1 Schonach - Martinskapelle",
      "Laenge": 14649,
      "TC": "",
      "HD": "",
      "Schwierigkeitsgrad": 39,
      "LL_Technik": 41,
      "s_cmp": "fernskiwanderweg schonach - belchen etappe 1 schonach - martinskapelle",
      "kats": [4],
      "trackstatus": 1,
      "rowpos": 31
    },
    {
      "ZID": 175,
      "SID": 2001,
      "STID": 187,
      "Sportart": 34,
      "Streckenname": "Fernskiwanderweg Schonach - Belchen Etappe 2 Martinskapelle - Kalte Herberge",
      "Laenge": 18619,
      "TC": "",
      "HD": "",
      "Schwierigkeitsgrad": 39,
      "LL_Technik": 41,
      "s_cmp": "fernskiwanderweg schonach - belchen etappe 2 martinskapelle - kalte herberge",
      "kats": [4],
      "trackstatus": 1,
      "rowpos": 32
    },
    {
      "ZID": 75,
      "SID": 2002,
      "STID": 181,
      "Sportart": 34,
      "Streckenname": "Fernskiwanderweg Schonach - Belchen Etappe 3 Kalte Herberge - Schweizer Hof",
      "Laenge": 6987,
      "TC": "",
      "HD": "",
      "Schwierigkeitsgrad": 39,
      "LL_Technik": 41,
      "s_cmp": "fernskiwanderweg schonach - belchen etappe 3 kalte herberge - schweizer hof",
      "kats": [4],
      "trackstatus": 1,
      "rowpos": 33
    },
    {
      "ZID": 70,
      "SID": 2003,
      "STID": 180,
      "Sportart": 34,
      "Streckenname": "Fernskiwanderweg Schonach - Belchen Etappe 4 Schweizer Hof - Breitnau",
      "Laenge": 13374,
      "TC": "",
      "HD": "",
      "Schwierigkeitsgrad": 39,
      "LL_Technik": 41,
      "s_cmp": "fernskiwanderweg schonach - belchen etappe 4 schweizer hof - breitnau",
      "kats": [4],
      "trackstatus": 1,
      "rowpos": 34
    },
    {
      "ZID": 20,
      "SID": 2004,
      "STID": 165,
      "Sportart": 34,
      "Streckenname": "Fernskiwanderweg Schonach - Belchen Etappe 5 Breitnau - Hinterzarten",
      "Laenge": 4339,
      "TC": "",
      "HD": "",
      "Schwierigkeitsgrad": 39,
      "LL_Technik": 41,
      "s_cmp": "fernskiwanderweg schonach - belchen etappe 5 breitnau - hinterzarten",
      "kats": [4],
      "trackstatus": 1,
      "rowpos": 35
    },
    {
      "ZID": 39,
      "SID": 2005,
      "STID": 161,
      "Sportart": 34,
      "Streckenname": "Fernskiwanderweg Schonach - Belchen Etappe 6 Hinterzarten - Rinken",
      "Laenge": 10212,
      "TC": "",
      "HD": "",
      "Schwierigkeitsgrad": 39,
      "LL_Technik": 41,
      "s_cmp": "fernskiwanderweg schonach - belchen etappe 6 hinterzarten - rinken",
      "kats": [4],
      "trackstatus": 1,
      "rowpos": 36
    },
    {
      "ZID": 117,
      "SID": 2006,
      "STID": 152,
      "Sportart": 34,
      "Streckenname": "Fernskiwanderweg Schonach - Belchen Etappe 7 Rinken - Todtnauer Hütte",
      "Laenge": 3333,
      "TC": "",
      "HD": "",
      "Schwierigkeitsgrad": 39,
      "LL_Technik": 41,
      "s_cmp": "fernskiwanderweg schonach - belchen etappe 7 rinken - todtnauer hutte",
      "kats": [4],
      "trackstatus": 1,
      "rowpos": 37
    },
    {
      "ZID": 60,
      "SID": 2007,
      "STID": 783,
      "Sportart": 34,
      "Streckenname": "Fernskiwanderweg Schonach - Belchen Etappe 8 Todtnauer Hütte - Wiedener Eck",
      "Laenge": 19470,
      "TC": 394,
      "HD": 354,
      "Schwierigkeitsgrad": 39,
      "LL_Technik": 41,
      "s_cmp": "fernskiwanderweg schonach - belchen etappe 8 todtnauer hutte - wiedener eck",
      "kats": [4],
      "trackstatus": 1,
      "rowpos": 38
    },
    {
      "ZID": 41,
      "SID": 2008,
      "STID": 140,
      "Sportart": 34,
      "Streckenname": "Fernskiwanderweg Schonach - Belchen Etappe 9 Wiedener Eck - Belchen-Multen",
      "Laenge": 9410,
      "TC": "",
      "HD": "",
      "Schwierigkeitsgrad": 39,
      "LL_Technik": 40,
      "s_cmp": "fernskiwanderweg schonach - belchen etappe 9 wiedener eck - belchen-multen",
      "kats": [4],
      "trackstatus": 1,
      "rowpos": 39
    },
    {
      "ZID": 186,
      "SID": 652,
      "STID": 813,
      "Sportart": 34,
      "Streckenname": "Fernskiwanderweg Schonach-Belchen",
      "Laenge": 100372,
      "TC": 394,
      "HD": 1389,
      "Schwierigkeitsgrad": 39,
      "LL_Technik": 41,
      "s_cmp": "fernskiwanderweg schonach-belchen",
      "kats": [4],
      "trackstatus": 1,
      "rowpos": 40
    },
    {
      "ZID": 17,
      "SID": 661,
      "STID": 120,
      "Sportart": 34,
      "Streckenname": "FIS Strecke",
      "Laenge": 3500,
      "TC": 132,
      "HD": 80,
      "Schwierigkeitsgrad": 39,
      "LL_Technik": 42,
      "s_cmp": "fis strecke",
      "kats": [5],
      "trackstatus": 1,
      "rowpos": 41
    },
    {
      "ZID": 68,
      "SID": 737,
      "STID": 130,
      "Sportart": 34,
      "Streckenname": "Fischbach - Spur",
      "Laenge": 7200,
      "TC": 169,
      "HD": 118,
      "Schwierigkeitsgrad": 38,
      "LL_Technik": 41,
      "s_cmp": "fischbach - spur",
      "kats": [2],
      "trackstatus": 1,
      "rowpos": 42
    },
    {
      "ZID": 39,
      "SID": 694,
      "STID": 153,
      "Sportart": 34,
      "Streckenname": "Fischloch - Loipe",
      "Laenge": 4100,
      "TC": 96,
      "HD": 78,
      "Schwierigkeitsgrad": 39,
      "LL_Technik": 40,
      "s_cmp": "fischloch - loipe",
      "kats": [],
      "trackstatus": 1,
      "rowpos": 43
    },
    {
      "ZID": 68,
      "SID": 738,
      "STID": 139,
      "Sportart": 34,
      "Streckenname": "Flutlicht - Spur",
      "Laenge": 1700,
      "TC": 37,
      "HD": 20,
      "Schwierigkeitsgrad": 38,
      "LL_Technik": 40,
      "s_cmp": "flutlicht - spur",
      "kats": [6],
      "trackstatus": 1,
      "rowpos": 44
    },
    {
      "ZID": 175,
      "SID": 670,
      "STID": 187,
      "Sportart": 34,
      "Streckenname": "Flutlicht Loipe",
      "Laenge": 2500,
      "TC": 54,
      "HD": 17,
      "Schwierigkeitsgrad": 38,
      "LL_Technik": 40,
      "s_cmp": "flutlicht loipe",
      "kats": [6],
      "trackstatus": 1,
      "rowpos": 45
    },
    {
      "ZID": 41,
      "SID": 705,
      "STID": 133,
      "Sportart": 34,
      "Streckenname": "Försterspur",
      "Laenge": 5600,
      "TC": 131,
      "HD": 70,
      "Schwierigkeitsgrad": 38,
      "LL_Technik": 40,
      "s_cmp": "forsterspur",
      "kats": [],
      "trackstatus": 1,
      "rowpos": 46
    },
    {
      "ZID": 117,
      "SID": 680,
      "STID": 143,
      "Sportart": 34,
      "Streckenname": "Freestyle - Runde",
      "Laenge": 1700,
      "TC": 36,
      "HD": 26,
      "Schwierigkeitsgrad": 38,
      "LL_Technik": 42,
      "s_cmp": "freestyle - runde",
      "kats": [],
      "trackstatus": 1,
      "rowpos": 47
    },
    {
      "ZID": 127,
      "SID": 1074,
      "STID": 115,
      "Sportart": 34,
      "Streckenname": "Fröhnd - Gresgener Höhenloipe",
      "Laenge": 22800,
      "TC": 550,
      "HD": 237,
      "Schwierigkeitsgrad": 39,
      "LL_Technik": 41,
      "s_cmp": "frohnd - gresgener hohenloipe",
      "kats": [3],
      "trackstatus": 0,
      "rowpos": 48
    },
    {
      "ZID": 39,
      "SID": 693,
      "STID": 153,
      "Sportart": 34,
      "Streckenname": "Fürsatz - Loipe",
      "Laenge": 10300,
      "TC": 129,
      "HD": 316,
      "Schwierigkeitsgrad": 39,
      "LL_Technik": 40,
      "s_cmp": "fursatz - loipe",
      "kats": [],
      "trackstatus": 1,
      "rowpos": 49
    },
    {
      "ZID": 75,
      "SID": 789,
      "STID": 163,
      "Sportart": 34,
      "Streckenname": "Fürsatzspur",
      "Laenge": 10000,
      "TC": 253,
      "HD": 202,
      "Schwierigkeitsgrad": 39,
      "LL_Technik": 41,
      "s_cmp": "fursatzspur",
      "kats": [],
      "trackstatus": 1,
      "rowpos": 50
    },
    {
      "ZID": 76,
      "SID": 794,
      "STID": 102,
      "Sportart": 34,
      "Streckenname": "Gersbacher - Spur",
      "Laenge": 11000,
      "TC": 268,
      "HD": 105,
      "Schwierigkeitsgrad": 39,
      "LL_Technik": 40,
      "s_cmp": "gersbacher - spur",
      "kats": [],
      "trackstatus": 1,
      "rowpos": 51
    },
    {
      "ZID": 179,
      "SID": 801,
      "STID": 190,
      "Sportart": 34,
      "Streckenname": "Geutsche - Loipe 3 km",
      "Laenge": 3100,
      "TC": 58,
      "HD": 49,
      "Schwierigkeitsgrad": 38,
      "LL_Technik": 41,
      "s_cmp": "geutsche - loipe 3 km",
      "kats": [],
      "trackstatus": 1,
      "rowpos": 52
    },
    {
      "ZID": 179,
      "SID": 802,
      "STID": 190,
      "Sportart": 34,
      "Streckenname": "Geutsche - Loipe 6 km",
      "Laenge": 6200,
      "TC": 143,
      "HD": 108,
      "Schwierigkeitsgrad": 39,
      "LL_Technik": 41,
      "s_cmp": "geutsche - loipe 6 km",
      "kats": [],
      "trackstatus": 1,
      "rowpos": 53
    },
    {
      "ZID": 139,
      "SID": 718,
      "STID": 118,
      "Sportart": 34,
      "Streckenname": "Gleichen Loipe",
      "Laenge": 8500,
      "TC": 147,
      "HD": 100,
      "Schwierigkeitsgrad": 38,
      "LL_Technik": 40,
      "s_cmp": "gleichen loipe",
      "kats": [],
      "trackstatus": 0,
      "rowpos": 54
    },
    {
      "ZID": 68,
      "SID": 739,
      "STID": 123,
      "Sportart": 34,
      "Streckenname": "Habsberg - Spur",
      "Laenge": 9500,
      "TC": 319,
      "HD": 120,
      "Schwierigkeitsgrad": 38,
      "LL_Technik": 41,
      "s_cmp": "habsberg - spur",
      "kats": [],
      "trackstatus": 1,
      "rowpos": 55
    },
    {
      "ZID": 60,
      "SID": 724,
      "STID": 789,
      "Sportart": 34,
      "Streckenname": "Haldenspur kurz",
      "Laenge": 1480,
      "TC": 29,
      "HD": 16,
      "Schwierigkeitsgrad": 37,
      "LL_Technik": 40,
      "s_cmp": "haldenspur kurz",
      "kats": [6],
      "trackstatus": 1,
      "rowpos": 56
    },
    {
      "ZID": 60,
      "SID": 725,
      "STID": 789,
      "Sportart": 34,
      "Streckenname": "Haldenspur lang",
      "Laenge": 2428,
      "TC": 50,
      "HD": 19,
      "Schwierigkeitsgrad": 39,
      "LL_Technik": 40,
      "s_cmp": "haldenspur lang",
      "kats": [],
      "trackstatus": 1,
      "rowpos": 57
    },
    {
      "ZID": 60,
      "SID": 12045,
      "STID": 789,
      "Sportart": 34,
      "Streckenname": "Haldenspur mittel",
      "Laenge": 2035,
      "TC": 45,
      "HD": 17,
      "Schwierigkeitsgrad": 39,
      "LL_Technik": 40,
      "s_cmp": "haldenspur mittel",
      "kats": [3],
      "trackstatus": 1,
      "rowpos": 58
    },
    {
      "ZID": 75,
      "SID": 785,
      "STID": 174,
      "Sportart": 34,
      "Streckenname": "Hellewand Spur",
      "Laenge": 1900,
      "TC": 55,
      "HD": 33,
      "Schwierigkeitsgrad": 38,
      "LL_Technik": 40,
      "s_cmp": "hellewand spur",
      "kats": [6],
      "trackstatus": 1,
      "rowpos": 59
    },
    {
      "ZID": 117,
      "SID": 681,
      "STID": 137,
      "Sportart": 34,
      "Streckenname": "Herzogenhorn Loipe",
      "Laenge": 3400,
      "TC": 81,
      "HD": 33,
      "Schwierigkeitsgrad": 38,
      "LL_Technik": 40,
      "s_cmp": "herzogenhorn loipe",
      "kats": [5],
      "trackstatus": 1,
      "rowpos": 60
    },
    {
      "ZID": 17,
      "SID": 657,
      "STID": 120,
      "Sportart": 34,
      "Streckenname": "Hexenbühl Loipe",
      "Laenge": 3400,
      "TC": 74,
      "HD": 49,
      "Schwierigkeitsgrad": 38,
      "LL_Technik": 40,
      "s_cmp": "hexenbuhl loipe",
      "kats": [],
      "trackstatus": 1,
      "rowpos": 61
    },
    {
      "ZID": 70,
      "SID": 772,
      "STID": 182,
      "Sportart": 34,
      "Streckenname": "Hirschen Spur",
      "Laenge": 2200,
      "TC": 34,
      "HD": 23,
      "Schwierigkeitsgrad": 37,
      "LL_Technik": 41,
      "s_cmp": "hirschen spur",
      "kats": [],
      "trackstatus": 1,
      "rowpos": 62
    },
    {
      "ZID": 173,
      "SID": 664,
      "STID": 175,
      "Sportart": 34,
      "Streckenname": "Hirschenberg Loipe",
      "Laenge": 1300,
      "TC": 34,
      "HD": 18,
      "Schwierigkeitsgrad": 38,
      "LL_Technik": 40,
      "s_cmp": "hirschenberg loipe",
      "kats": [6],
      "trackstatus": 1,
      "rowpos": 63
    },
    {
      "ZID": 75,
      "SID": 786,
      "STID": 176,
      "Sportart": 34,
      "Streckenname": "Hochberg Spur",
      "Laenge": 2100,
      "TC": 68,
      "HD": 62,
      "Schwierigkeitsgrad": 38,
      "LL_Technik": 41,
      "s_cmp": "hochberg spur",
      "kats": [],
      "trackstatus": 1,
      "rowpos": 64
    },
    {
      "ZID": 75,
      "SID": 783,
      "STID": 171,
      "Sportart": 34,
      "Streckenname": "Hochebene Spur I",
      "Laenge": 2200,
      "TC": 49,
      "HD": 33,
      "Schwierigkeitsgrad": 38,
      "LL_Technik": 41,
      "s_cmp": "hochebene spur i",
      "kats": [],
      "trackstatus": 1,
      "rowpos": 65
    },
    {
      "ZID": 75,
      "SID": 784,
      "STID": 171,
      "Sportart": 34,
      "Streckenname": "Hochebene Spur II",
      "Laenge": 1900,
      "TC": 40,
      "HD": 25,
      "Schwierigkeitsgrad": 38,
      "LL_Technik": 42,
      "s_cmp": "hochebene spur ii",
      "kats": [],
      "trackstatus": 1,
      "rowpos": 66
    },
    {
      "ZID": 187,
      "SID": 698,
      "STID": 106,
      "Sportart": 34,
      "Streckenname": "Höchenschwander - Moor - Loipe",
      "Laenge": 2000,
      "TC": 26,
      "HD": 19,
      "Schwierigkeitsgrad": 37,
      "LL_Technik": 41,
      "s_cmp": "hochenschwander - moor - loipe",
      "kats": [1],
      "trackstatus": 1,
      "rowpos": 67
    },
    {
      "ZID": 137,
      "SID": 715,
      "STID": 156,
      "Sportart": 34,
      "Streckenname": "Hochfirstspur",
      "Laenge": 9900,
      "TC": 223,
      "HD": 147,
      "Schwierigkeitsgrad": 39,
      "LL_Technik": 41,
      "s_cmp": "hochfirstspur",
      "kats": [],
      "trackstatus": 1,
      "rowpos": 68
    },
    {
      "ZID": 39,
      "SID": 689,
      "STID": 160,
      "Sportart": 34,
      "Streckenname": "Hochmoor - Loipe",
      "Laenge": 5500,
      "TC": 51,
      "HD": 25,
      "Schwierigkeitsgrad": 37,
      "LL_Technik": 40,
      "s_cmp": "hochmoor - loipe",
      "kats": [1],
      "trackstatus": 1,
      "rowpos": 69
    },
    {
      "ZID": 173,
      "SID": 663,
      "STID": 170,
      "Sportart": 34,
      "Streckenname": "Höchst Spur",
      "Laenge": 8800,
      "TC": 160,
      "HD": 78,
      "Schwierigkeitsgrad": 38,
      "LL_Technik": 40,
      "s_cmp": "hochst spur",
      "kats": [],
      "trackstatus": 1,
      "rowpos": 70
    },
    {
      "ZID": 173,
      "SID": 662,
      "STID": 169,
      "Sportart": 34,
      "Streckenname": "Höchstberg Loipe",
      "Laenge": 2000,
      "TC": 17,
      "HD": 12,
      "Schwierigkeitsgrad": 37,
      "LL_Technik": 40,
      "s_cmp": "hochstberg loipe",
      "kats": [1],
      "trackstatus": 1,
      "rowpos": 71
    },
    {
      "ZID": 178,
      "SID": 764,
      "STID": 193,
      "Sportart": 34,
      "Streckenname": "Hochwaldloipe",
      "Laenge": 10600,
      "TC": 134,
      "HD": 69,
      "Schwierigkeitsgrad": 38,
      "LL_Technik": 41,
      "s_cmp": "hochwaldloipe",
      "kats": [],
      "trackstatus": 1,
      "rowpos": 72
    },
    {
      "ZID": 110,
      "SID": 775,
      "STID": 184,
      "Sportart": 34,
      "Streckenname": "Hochwaldloipe I",
      "Laenge": 4700,
      "TC": 142,
      "HD": 58,
      "Schwierigkeitsgrad": 39,
      "LL_Technik": 42,
      "s_cmp": "hochwaldloipe i",
      "kats": [],
      "trackstatus": 1,
      "rowpos": 73
    },
    {
      "ZID": 110,
      "SID": 776,
      "STID": 184,
      "Sportart": 34,
      "Streckenname": "Hochwaldloipe II",
      "Laenge": 6500,
      "TC": 232,
      "HD": 60,
      "Schwierigkeitsgrad": 39,
      "LL_Technik": 41,
      "s_cmp": "hochwaldloipe ii",
      "kats": [3],
      "trackstatus": 1,
      "rowpos": 74
    },
    {
      "ZID": 17,
      "SID": 653,
      "STID": 126,
      "Sportart": 34,
      "Streckenname": "Hof Loipe",
      "Laenge": 2700,
      "TC": 23,
      "HD": 16,
      "Schwierigkeitsgrad": 37,
      "LL_Technik": 40,
      "s_cmp": "hof loipe",
      "kats": [],
      "trackstatus": 1,
      "rowpos": 75
    },
    {
      "ZID": 173,
      "SID": 665,
      "STID": 179,
      "Sportart": 34,
      "Streckenname": "Höfe Spur",
      "Laenge": 8000,
      "TC": 208,
      "HD": 96,
      "Schwierigkeitsgrad": 38,
      "LL_Technik": 41,
      "s_cmp": "hofe spur",
      "kats": [],
      "trackstatus": 1,
      "rowpos": 76
    },
    {
      "ZID": 20,
      "SID": 1063,
      "STID": 167,
      "Sportart": 34,
      "Streckenname": "Hohschachen - Loipe",
      "Laenge": 3500,
      "TC": 63,
      "HD": 47,
      "Schwierigkeitsgrad": 37,
      "LL_Technik": 41,
      "s_cmp": "hohschachen - loipe",
      "kats": [6],
      "trackstatus": 1,
      "rowpos": 77
    },
    {
      "ZID": 174,
      "SID": 796,
      "STID": 782,
      "Sportart": 34,
      "Streckenname": "Hornloipe",
      "Laenge": 2500,
      "TC": 45,
      "HD": 36,
      "Schwierigkeitsgrad": 37,
      "LL_Technik": 40,
      "s_cmp": "hornloipe",
      "kats": [],
      "trackstatus": 0,
      "rowpos": 78
    },
    {
      "ZID": 75,
      "SID": 788,
      "STID": 164,
      "Sportart": 34,
      "Streckenname": "Jostalspur",
      "Laenge": 8100,
      "TC": 281,
      "HD": 181,
      "Schwierigkeitsgrad": 39,
      "LL_Technik": 40,
      "s_cmp": "jostalspur",
      "kats": [3],
      "trackstatus": 1,
      "rowpos": 79
    },
    {
      "ZID": 174,
      "SID": 800,
      "STID": 782,
      "Sportart": 34,
      "Streckenname": "Kapellenrunde",
      "Laenge": 11500,
      "TC": 327,
      "HD": 204,
      "Schwierigkeitsgrad": 39,
      "LL_Technik": 40,
      "s_cmp": "kapellenrunde",
      "kats": [],
      "trackstatus": 0,
      "rowpos": 80
    },
    {
      "ZID": 70,
      "SID": 773,
      "STID": 182,
      "Sportart": 34,
      "Streckenname": "Kapfenberg Loipe",
      "Laenge": 7300,
      "TC": 177,
      "HD": 130,
      "Schwierigkeitsgrad": 39,
      "LL_Technik": 41,
      "s_cmp": "kapfenberg loipe",
      "kats": [],
      "trackstatus": 1,
      "rowpos": 81
    },
    {
      "ZID": 42,
      "SID": 678,
      "STID": 101,
      "Sportart": 34,
      "Streckenname": "Klausenhof Loipe",
      "Laenge": 8300,
      "TC": 164,
      "HD": 59,
      "Schwierigkeitsgrad": 39,
      "LL_Technik": 41,
      "s_cmp": "klausenhof loipe",
      "kats": [],
      "trackstatus": 1,
      "rowpos": 82
    },
    {
      "ZID": 69,
      "SID": 762,
      "STID": 112,
      "Sportart": 34,
      "Streckenname": "Kohlwaldloipe",
      "Laenge": 10200,
      "TC": 285,
      "HD": 109,
      "Schwierigkeitsgrad": 39,
      "LL_Technik": 41,
      "s_cmp": "kohlwaldloipe",
      "kats": [3],
      "trackstatus": 1,
      "rowpos": 83
    },
    {
      "ZID": 117,
      "SID": 679,
      "STID": 144,
      "Sportart": 34,
      "Streckenname": "Köpfle - Loipe",
      "Laenge": 3300,
      "TC": 78,
      "HD": 41,
      "Schwierigkeitsgrad": 38,
      "LL_Technik": 41,
      "s_cmp": "kopfle - loipe",
      "kats": [],
      "trackstatus": 1,
      "rowpos": 84
    },
    {
      "ZID": 41,
      "SID": 704,
      "STID": 134,
      "Sportart": 34,
      "Streckenname": "Kostloipe",
      "Laenge": 7500,
      "TC": 173,
      "HD": 92,
      "Schwierigkeitsgrad": 38,
      "LL_Technik": 40,
      "s_cmp": "kostloipe",
      "kats": [],
      "trackstatus": 1,
      "rowpos": 85
    },
    {
      "ZID": 187,
      "SID": 702,
      "STID": 106,
      "Sportart": 34,
      "Streckenname": "Kreuzstein - Loipe",
      "Laenge": 4500,
      "TC": 89,
      "HD": 61,
      "Schwierigkeitsgrad": 39,
      "LL_Technik": 41,
      "s_cmp": "kreuzstein - loipe",
      "kats": [],
      "trackstatus": 1,
      "rowpos": 86
    },
    {
      "ZID": 69,
      "SID": 761,
      "STID": 136,
      "Sportart": 34,
      "Streckenname": "Kurhausloipe",
      "Laenge": 5100,
      "TC": 114,
      "HD": 47,
      "Schwierigkeitsgrad": 38,
      "LL_Technik": 41,
      "s_cmp": "kurhausloipe",
      "kats": [],
      "trackstatus": 1,
      "rowpos": 87
    },
    {
      "ZID": 174,
      "SID": 798,
      "STID": 782,
      "Sportart": 34,
      "Streckenname": "Kurze Panoramarunde",
      "Laenge": 13210,
      "TC": 67,
      "HD": 1355,
      "Schwierigkeitsgrad": 39,
      "LL_Technik": 40,
      "s_cmp": "kurze panoramarunde",
      "kats": [],
      "trackstatus": 1,
      "rowpos": 88
    },
    {
      "ZID": 174,
      "SID": 799,
      "STID": 782,
      "Sportart": 34,
      "Streckenname": "Lange Panoramarunde",
      "Laenge": 21346,
      "TC": 163,
      "HD": 1389,
      "Schwierigkeitsgrad": 39,
      "LL_Technik": 40,
      "s_cmp": "lange panoramarunde",
      "kats": [3],
      "trackstatus": 1,
      "rowpos": 89
    },
    {
      "ZID": 75,
      "SID": 787,
      "STID": 178,
      "Sportart": 34,
      "Streckenname": "Langenordnachspur",
      "Laenge": 7600,
      "TC": 21,
      "HD": 77,
      "Schwierigkeitsgrad": 37,
      "LL_Technik": 40,
      "s_cmp": "langenordnachspur",
      "kats": [],
      "trackstatus": 1,
      "rowpos": 90
    },
    {
      "ZID": 176,
      "SID": 749,
      "STID": 813,
      "Sportart": 34,
      "Streckenname": "Langenwald - Loipe",
      "Laenge": 4600,
      "TC": 150,
      "HD": 116,
      "Schwierigkeitsgrad": 39,
      "LL_Technik": 40,
      "s_cmp": "langenwald - loipe",
      "kats": [],
      "trackstatus": 0,
      "rowpos": 91
    },
    {
      "ZID": 17,
      "SID": 659,
      "STID": 120,
      "Sportart": 34,
      "Streckenname": "Langhalden Loipe",
      "Laenge": 9700,
      "TC": 235,
      "HD": 110,
      "Schwierigkeitsgrad": 39,
      "LL_Technik": 41,
      "s_cmp": "langhalden loipe",
      "kats": [],
      "trackstatus": 1,
      "rowpos": 92
    },
    {
      "ZID": 17,
      "SID": 658,
      "STID": 125,
      "Sportart": 34,
      "Streckenname": "Lehen Loipe",
      "Laenge": 4300,
      "TC": 76,
      "HD": 47,
      "Schwierigkeitsgrad": 38,
      "LL_Technik": 41,
      "s_cmp": "lehen loipe",
      "kats": [2],
      "trackstatus": 1,
      "rowpos": 93
    },
    {
      "ZID": 187,
      "SID": 700,
      "STID": 109,
      "Sportart": 34,
      "Streckenname": "Loipenhaus - Loipe",
      "Laenge": 9300,
      "TC": 193,
      "HD": 114,
      "Schwierigkeitsgrad": 38,
      "LL_Technik": 41,
      "s_cmp": "loipenhaus - loipe",
      "kats": [],
      "trackstatus": 1,
      "rowpos": 94
    },
    {
      "ZID": 176,
      "SID": 745,
      "STID": 194,
      "Sportart": 34,
      "Streckenname": "Loipenhausrunde",
      "Laenge": 2000,
      "TC": 46,
      "HD": 29,
      "Schwierigkeitsgrad": 38,
      "LL_Technik": 40,
      "s_cmp": "loipenhausrunde",
      "kats": [],
      "trackstatus": 0,
      "rowpos": 95
    },
    {
      "ZID": 139,
      "SID": 720,
      "STID": 118,
      "Sportart": 34,
      "Streckenname": "Meierskopf Loipe",
      "Laenge": 12400,
      "TC": 266,
      "HD": 199,
      "Schwierigkeitsgrad": 39,
      "LL_Technik": 40,
      "s_cmp": "meierskopf loipe",
      "kats": [],
      "trackstatus": 0,
      "rowpos": 96
    },
    {
      "ZID": 69,
      "SID": 763,
      "STID": 132,
      "Sportart": 34,
      "Streckenname": "Menzenschwander Spur",
      "Laenge": 8300,
      "TC": 152,
      "HD": 97,
      "Schwierigkeitsgrad": 39,
      "LL_Technik": 41,
      "s_cmp": "menzenschwander spur",
      "kats": [],
      "trackstatus": 1,
      "rowpos": 97
    },
    {
      "ZID": 68,
      "SID": 742,
      "STID": 132,
      "Sportart": 34,
      "Streckenname": "Menzenschwander Spur",
      "Laenge": 8300,
      "TC": 152,
      "HD": 97,
      "Schwierigkeitsgrad": 39,
      "LL_Technik": 41,
      "s_cmp": "menzenschwander spur",
      "kats": [],
      "trackstatus": 1,
      "rowpos": 98
    },
    {
      "ZID": 176,
      "SID": 747,
      "STID": 194,
      "Sportart": 34,
      "Streckenname": "Moos - Loipe",
      "Laenge": 7600,
      "TC": 162,
      "HD": 46,
      "Schwierigkeitsgrad": 38,
      "LL_Technik": 40,
      "s_cmp": "moos - loipe",
      "kats": [],
      "trackstatus": 0,
      "rowpos": 99
    },
    {
      "ZID": 75,
      "SID": 778,
      "STID": 158,
      "Sportart": 34,
      "Streckenname": "Mooswaldspur",
      "Laenge": 3600,
      "TC": 68,
      "HD": 40,
      "Schwierigkeitsgrad": 38,
      "LL_Technik": 40,
      "s_cmp": "mooswaldspur",
      "kats": [6],
      "trackstatus": 1,
      "rowpos": 100
    },
    {
      "ZID": 42,
      "SID": 674,
      "STID": 100,
      "Sportart": 34,
      "Streckenname": "Mösle Loipe",
      "Laenge": 6200,
      "TC": 100,
      "HD": 50,
      "Schwierigkeitsgrad": 38,
      "LL_Technik": 41,
      "s_cmp": "mosle loipe",
      "kats": [],
      "trackstatus": 1,
      "rowpos": 101
    },
    {
      "ZID": 69,
      "SID": 760,
      "STID": 136,
      "Sportart": 34,
      "Streckenname": "Mösleloipe",
      "Laenge": 2300,
      "TC": 29,
      "HD": 28,
      "Schwierigkeitsgrad": 37,
      "LL_Technik": 42,
      "s_cmp": "mosleloipe",
      "kats": [],
      "trackstatus": 1,
      "rowpos": 102
    },
    {
      "ZID": 69,
      "SID": 759,
      "STID": 136,
      "Sportart": 34,
      "Streckenname": "Mösleloipe",
      "Laenge": 2800,
      "TC": 33,
      "HD": 32,
      "Schwierigkeitsgrad": 37,
      "LL_Technik": 41,
      "s_cmp": "mosleloipe",
      "kats": [1],
      "trackstatus": 1,
      "rowpos": 103
    },
    {
      "ZID": 137,
      "SID": 713,
      "STID": 151,
      "Sportart": 34,
      "Streckenname": "Mühlinger Trainingsspur",
      "Laenge": 1600,
      "TC": 30,
      "HD": 24,
      "Schwierigkeitsgrad": 37,
      "LL_Technik": 41,
      "s_cmp": "muhlinger trainingsspur",
      "kats": [1, 6],
      "trackstatus": 1,
      "rowpos": 104
    },
    {
      "ZID": 143,
      "SID": 1066,
      "STID": 173,
      "Sportart": 34,
      "Streckenname": "Nachtloipe",
      "Laenge": 2300,
      "TC": 33,
      "HD": 26,
      "Schwierigkeitsgrad": 37,
      "LL_Technik": 41,
      "s_cmp": "nachtloipe",
      "kats": [6],
      "trackstatus": 1,
      "rowpos": 106
    },
    {
      "ZID": 70,
      "SID": 863,
      "STID": 177,
      "Sportart": 34,
      "Streckenname": "Nachtloipe",
      "Laenge": 2200,
      "TC": "",
      "HD": "",
      "Schwierigkeitsgrad": 37,
      "LL_Technik": 40,
      "s_cmp": "nachtloipe",
      "kats": [6],
      "trackstatus": 1,
      "rowpos": 105
    },
    {
      "ZID": 175,
      "SID": 666,
      "STID": 183,
      "Sportart": 34,
      "Streckenname": "Neukircher Strecke",
      "Laenge": 1900,
      "TC": 45,
      "HD": 37,
      "Schwierigkeitsgrad": 37,
      "LL_Technik": 40,
      "s_cmp": "neukircher strecke",
      "kats": [],
      "trackstatus": 1,
      "rowpos": 107
    },
    {
      "ZID": 139,
      "SID": 721,
      "STID": 124,
      "Sportart": 34,
      "Streckenname": "Nonnemattweiher Loipe",
      "Laenge": 17000,
      "TC": 390,
      "HD": 232,
      "Schwierigkeitsgrad": 39,
      "LL_Technik": 40,
      "s_cmp": "nonnemattweiher loipe",
      "kats": [3],
      "trackstatus": 0,
      "rowpos": 108
    },
    {
      "ZID": 143,
      "SID": 1068,
      "STID": 173,
      "Sportart": 34,
      "Streckenname": "Oberholzloipe",
      "Laenge": 8800,
      "TC": 111,
      "HD": 77,
      "Schwierigkeitsgrad": 39,
      "LL_Technik": 41,
      "s_cmp": "oberholzloipe",
      "kats": [],
      "trackstatus": 1,
      "rowpos": 109
    },
    {
      "ZID": 39,
      "SID": 695,
      "STID": 162,
      "Sportart": 34,
      "Streckenname": "Oberzartener - Loipe",
      "Laenge": 7900,
      "TC": 189,
      "HD": 132,
      "Schwierigkeitsgrad": 39,
      "LL_Technik": 40,
      "s_cmp": "oberzartener - loipe",
      "kats": [],
      "trackstatus": 1,
      "rowpos": 110
    },
    {
      "ZID": 42,
      "SID": 677,
      "STID": 101,
      "Sportart": 34,
      "Streckenname": "Ödland Loipe",
      "Laenge": 16000,
      "TC": 296,
      "HD": 106,
      "Schwierigkeitsgrad": 39,
      "LL_Technik": 41,
      "s_cmp": "odland loipe",
      "kats": [3],
      "trackstatus": 1,
      "rowpos": 111
    },
    {
      "ZID": 17,
      "SID": 660,
      "STID": 120,
      "Sportart": 34,
      "Streckenname": "Oren Loipe",
      "Laenge": 6400,
      "TC": 180,
      "HD": 109,
      "Schwierigkeitsgrad": 39,
      "LL_Technik": 41,
      "s_cmp": "oren loipe",
      "kats": [],
      "trackstatus": 1,
      "rowpos": 112
    },
    {
      "ZID": 40,
      "SID": 1062,
      "STID": 114,
      "Sportart": 34,
      "Streckenname": "Panorama - Loipe",
      "Laenge": 2600,
      "TC": 44,
      "HD": 31,
      "Schwierigkeitsgrad": 37,
      "LL_Technik": 41,
      "s_cmp": "panorama - loipe",
      "kats": [2],
      "trackstatus": 1,
      "rowpos": 113
    },
    {
      "ZID": 176,
      "SID": 746,
      "STID": 194,
      "Sportart": 34,
      "Streckenname": "Panorama - Loipe",
      "Laenge": 11800,
      "TC": 269,
      "HD": 87,
      "Schwierigkeitsgrad": 38,
      "LL_Technik": 40,
      "s_cmp": "panorama - loipe",
      "kats": [2],
      "trackstatus": 0,
      "rowpos": 115
    },
    {
      "ZID": 20,
      "SID": 1065,
      "STID": 167,
      "Sportart": 34,
      "Streckenname": "Panorama - Loipe",
      "Laenge": 7800,
      "TC": 182,
      "HD": 89,
      "Schwierigkeitsgrad": 38,
      "LL_Technik": 41,
      "s_cmp": "panorama - loipe",
      "kats": [2],
      "trackstatus": 1,
      "rowpos": 114
    },
    {
      "ZID": 175,
      "SID": 667,
      "STID": 187,
      "Sportart": 34,
      "Streckenname": "Panorama Loipe",
      "Laenge": 6600,
      "TC": 143,
      "HD": 58,
      "Schwierigkeitsgrad": 37,
      "LL_Technik": 40,
      "s_cmp": "panorama loipe",
      "kats": [2],
      "trackstatus": 1,
      "rowpos": 116
    },
    {
      "ZID": 75,
      "SID": 777,
      "STID": 171,
      "Sportart": 34,
      "Streckenname": "Panorama Spur",
      "Laenge": 3600,
      "TC": 83,
      "HD": 49,
      "Schwierigkeitsgrad": 37,
      "LL_Technik": 40,
      "s_cmp": "panorama spur",
      "kats": [2],
      "trackstatus": 1,
      "rowpos": 117
    },
    {
      "ZID": 41,
      "SID": 706,
      "STID": 133,
      "Sportart": 34,
      "Streckenname": "Panoramaspur",
      "Laenge": 11800,
      "TC": 352,
      "HD": 225,
      "Schwierigkeitsgrad": 39,
      "LL_Technik": 40,
      "s_cmp": "panoramaspur",
      "kats": [3],
      "trackstatus": 1,
      "rowpos": 118
    },
    {
      "ZID": 75,
      "SID": 790,
      "STID": 171,
      "Sportart": 34,
      "Streckenname": "Panoramawald Spur",
      "Laenge": 5900,
      "TC": 134,
      "HD": 62,
      "Schwierigkeitsgrad": 39,
      "LL_Technik": 41,
      "s_cmp": "panoramawald spur",
      "kats": [],
      "trackstatus": 1,
      "rowpos": 119
    },
    {
      "ZID": 178,
      "SID": 768,
      "STID": 195,
      "Sportart": 34,
      "Streckenname": "Peterzeller Loipe",
      "Laenge": 5200,
      "TC": 113,
      "HD": 97,
      "Schwierigkeitsgrad": 39,
      "LL_Technik": 42,
      "s_cmp": "peterzeller loipe",
      "kats": [],
      "trackstatus": 1,
      "rowpos": 120
    },
    {
      "ZID": 178,
      "SID": 767,
      "STID": 195,
      "Sportart": 34,
      "Streckenname": "Peterzeller Loipe",
      "Laenge": 12300,
      "TC": 210,
      "HD": 133,
      "Schwierigkeitsgrad": 39,
      "LL_Technik": 41,
      "s_cmp": "peterzeller loipe",
      "kats": [],
      "trackstatus": 1,
      "rowpos": 121
    },
    {
      "ZID": 137,
      "SID": 716,
      "STID": 141,
      "Sportart": 34,
      "Streckenname": "Pflumbergspur",
      "Laenge": 4300,
      "TC": 89,
      "HD": 64,
      "Schwierigkeitsgrad": 39,
      "LL_Technik": 41,
      "s_cmp": "pflumbergspur",
      "kats": [],
      "trackstatus": 1,
      "rowpos": 122
    },
    {
      "ZID": 17,
      "SID": 656,
      "STID": 120,
      "Sportart": 34,
      "Streckenname": "Rechberg Loipe",
      "Laenge": 5800,
      "TC": 143,
      "HD": 70,
      "Schwierigkeitsgrad": 38,
      "LL_Technik": 41,
      "s_cmp": "rechberg loipe",
      "kats": [],
      "trackstatus": 1,
      "rowpos": 123
    },
    {
      "ZID": 69,
      "SID": 758,
      "STID": 128,
      "Sportart": 34,
      "Streckenname": "Rehbachloipe",
      "Laenge": 3800,
      "TC": 28,
      "HD": 12,
      "Schwierigkeitsgrad": 37,
      "LL_Technik": 41,
      "s_cmp": "rehbachloipe",
      "kats": [],
      "trackstatus": 1,
      "rowpos": 124
    },
    {
      "ZID": 75,
      "SID": 791,
      "STID": 171,
      "Sportart": 34,
      "Streckenname": "Reichenbach Spur",
      "Laenge": 4700,
      "TC": 22,
      "HD": 232,
      "Schwierigkeitsgrad": 39,
      "LL_Technik": 41,
      "s_cmp": "reichenbach spur",
      "kats": [],
      "trackstatus": 1,
      "rowpos": 125
    },
    {
      "ZID": 143,
      "SID": 1067,
      "STID": 173,
      "Sportart": 34,
      "Streckenname": "Rimsen - Loipe",
      "Laenge": 4100,
      "TC": 43,
      "HD": 26,
      "Schwierigkeitsgrad": 38,
      "LL_Technik": 41,
      "s_cmp": "rimsen - loipe",
      "kats": [],
      "trackstatus": 1,
      "rowpos": 126
    },
    {
      "ZID": 39,
      "SID": 691,
      "STID": 153,
      "Sportart": 34,
      "Streckenname": "Rinken - Loipe",
      "Laenge": 8000,
      "TC": 154,
      "HD": 133,
      "Schwierigkeitsgrad": 38,
      "LL_Technik": 40,
      "s_cmp": "rinken - loipe",
      "kats": [],
      "trackstatus": 1,
      "rowpos": 127
    },
    {
      "ZID": 175,
      "SID": 669,
      "STID": 187,
      "Sportart": 34,
      "Streckenname": "Roßeck Strecke",
      "Laenge": 7700,
      "TC": 165,
      "HD": 67,
      "Schwierigkeitsgrad": 38,
      "LL_Technik": 41,
      "s_cmp": "roseck strecke",
      "kats": [],
      "trackstatus": 1,
      "rowpos": 128
    },
    {
      "ZID": 68,
      "SID": 736,
      "STID": 131,
      "Sportart": 34,
      "Streckenname": "Roßwasen - Spur",
      "Laenge": 3800,
      "TC": 79,
      "HD": 63,
      "Schwierigkeitsgrad": 38,
      "LL_Technik": 40,
      "s_cmp": "roswasen - spur",
      "kats": [],
      "trackstatus": 1,
      "rowpos": 129
    },
    {
      "ZID": 205,
      "SID": 1056,
      "STID": 185,
      "Sportart": 34,
      "Streckenname": "Rote Strecke",
      "Laenge": 5800,
      "TC": 170,
      "HD": 81,
      "Schwierigkeitsgrad": 38,
      "LL_Technik": 40,
      "s_cmp": "rote strecke",
      "kats": [],
      "trackstatus": 1,
      "rowpos": 130
    },
    {
      "ZID": 177,
      "SID": 756,
      "STID": 189,
      "Sportart": 34,
      "Streckenname": "Rothausloipenzentrum",
      "Laenge": 2500,
      "TC": 66,
      "HD": 37,
      "Schwierigkeitsgrad": 39,
      "LL_Technik": 40,
      "s_cmp": "rothausloipenzentrum",
      "kats": [5, 6, 7],
      "trackstatus": 1,
      "rowpos": 131
    },
    {
      "ZID": 137,
      "SID": 714,
      "STID": 157,
      "Sportart": 34,
      "Streckenname": "Rotkreuzspur",
      "Laenge": 6000,
      "TC": 129,
      "HD": 48,
      "Schwierigkeitsgrad": 38,
      "LL_Technik": 41,
      "s_cmp": "rotkreuzspur",
      "kats": [2],
      "trackstatus": 1,
      "rowpos": 132
    },
    {
      "ZID": 117,
      "SID": 687,
      "STID": 145,
      "Sportart": 34,
      "Streckenname": "Rotmeer Loipe I",
      "Laenge": 9500,
      "TC": 187,
      "HD": 128,
      "Schwierigkeitsgrad": 39,
      "LL_Technik": 41,
      "s_cmp": "rotmeer loipe i",
      "kats": [],
      "trackstatus": 1,
      "rowpos": 133
    },
    {
      "ZID": 117,
      "SID": 686,
      "STID": 145,
      "Sportart": 34,
      "Streckenname": "Rotmeer Loipe II",
      "Laenge": 3300,
      "TC": 43,
      "HD": 21,
      "Schwierigkeitsgrad": 38,
      "LL_Technik": 41,
      "s_cmp": "rotmeer loipe ii",
      "kats": [],
      "trackstatus": 1,
      "rowpos": 134
    },
    {
      "ZID": 75,
      "SID": 782,
      "STID": 168,
      "Sportart": 34,
      "Streckenname": "Rudenberg Spur",
      "Laenge": 4000,
      "TC": 28,
      "HD": 31,
      "Schwierigkeitsgrad": 38,
      "LL_Technik": 41,
      "s_cmp": "rudenberg spur",
      "kats": [],
      "trackstatus": 1,
      "rowpos": 135
    },
    {
      "ZID": 177,
      "SID": 752,
      "STID": 188,
      "Sportart": 34,
      "Streckenname": "Rundloipe im Landschaftsgarten",
      "Laenge": 900,
      "TC": 14,
      "HD": 12,
      "Schwierigkeitsgrad": 37,
      "LL_Technik": 41,
      "s_cmp": "rundloipe im landschaftsgarten",
      "kats": [],
      "trackstatus": 1,
      "rowpos": 136
    },
    {
      "ZID": 75,
      "SID": 779,
      "STID": 178,
      "Sportart": 34,
      "Streckenname": "Rundloipe Waldau",
      "Laenge": 7500,
      "TC": 182,
      "HD": 119,
      "Schwierigkeitsgrad": 38,
      "LL_Technik": 40,
      "s_cmp": "rundloipe waldau",
      "kats": [],
      "trackstatus": 1,
      "rowpos": 137
    },
    {
      "ZID": 68,
      "SID": 735,
      "STID": 130,
      "Sportart": 34,
      "Streckenname": "Rundspur",
      "Laenge": 1400,
      "TC": 23,
      "HD": 18,
      "Schwierigkeitsgrad": 37,
      "LL_Technik": 41,
      "s_cmp": "rundspur",
      "kats": [1],
      "trackstatus": 1,
      "rowpos": 138
    },
    {
      "ZID": 177,
      "SID": 753,
      "STID": 186,
      "Sportart": 34,
      "Streckenname": "Schaibenloipe",
      "Laenge": 4700,
      "TC": 108,
      "HD": 61,
      "Schwierigkeitsgrad": 38,
      "LL_Technik": 41,
      "s_cmp": "schaibenloipe",
      "kats": [],
      "trackstatus": 1,
      "rowpos": 139
    },
    {
      "ZID": 175,
      "SID": 671,
      "STID": 191,
      "Sportart": 34,
      "Streckenname": "Schänzle Loipe",
      "Laenge": 6000,
      "TC": 121,
      "HD": 90,
      "Schwierigkeitsgrad": 39,
      "LL_Technik": 41,
      "s_cmp": "schanzle loipe",
      "kats": [],
      "trackstatus": 1,
      "rowpos": 140
    },
    {
      "ZID": 60,
      "SID": 722,
      "STID": 784,
      "Sportart": 34,
      "Streckenname": "Schauinslandspur",
      "Laenge": 16933,
      "TC": 434,
      "HD": 146,
      "Schwierigkeitsgrad": 38,
      "LL_Technik": 40,
      "s_cmp": "schauinslandspur",
      "kats": [2],
      "trackstatus": 1,
      "rowpos": 141
    },
    {
      "ZID": 68,
      "SID": 743,
      "STID": 131,
      "Sportart": 34,
      "Streckenname": "Schluchsee - Spur",
      "Laenge": 9000,
      "TC": 205,
      "HD": 102,
      "Schwierigkeitsgrad": 39,
      "LL_Technik": 41,
      "s_cmp": "schluchsee - spur",
      "kats": [],
      "trackstatus": 1,
      "rowpos": 142
    },
    {
      "ZID": 68,
      "SID": 744,
      "STID": 117,
      "Sportart": 34,
      "Streckenname": "Schönenbach - Spur",
      "Laenge": 6100,
      "TC": 140,
      "HD": 74,
      "Schwierigkeitsgrad": 39,
      "LL_Technik": 41,
      "s_cmp": "schonenbach - spur",
      "kats": [],
      "trackstatus": 1,
      "rowpos": 143
    },
    {
      "ZID": 187,
      "SID": 701,
      "STID": 106,
      "Sportart": 34,
      "Streckenname": "Schwarzahang - Loipe",
      "Laenge": 13200,
      "TC": 282,
      "HD": 178,
      "Schwierigkeitsgrad": 39,
      "LL_Technik": 41,
      "s_cmp": "schwarzahang - loipe",
      "kats": [3],
      "trackstatus": 1,
      "rowpos": 144
    },
    {
      "ZID": 69,
      "SID": 757,
      "STID": 119,
      "Sportart": 34,
      "Streckenname": "Schwimmbadloipe",
      "Laenge": 3900,
      "TC": 27,
      "HD": 18,
      "Schwierigkeitsgrad": 37,
      "LL_Technik": 40,
      "s_cmp": "schwimmbadloipe",
      "kats": [],
      "trackstatus": 1,
      "rowpos": 145
    },
    {
      "ZID": 39,
      "SID": 688,
      "STID": 154,
      "Sportart": 34,
      "Streckenname": "Seebach - Loipe",
      "Laenge": 4300,
      "TC": 25,
      "HD": 10,
      "Schwierigkeitsgrad": 37,
      "LL_Technik": 41,
      "s_cmp": "seebach - loipe",
      "kats": [],
      "trackstatus": 1,
      "rowpos": 146
    },
    {
      "ZID": 126,
      "SID": 731,
      "STID": 122,
      "Sportart": 34,
      "Streckenname": "Signau Loipe",
      "Laenge": 4800,
      "TC": 61,
      "HD": 28,
      "Schwierigkeitsgrad": 38,
      "LL_Technik": 41,
      "s_cmp": "signau loipe",
      "kats": [],
      "trackstatus": 1,
      "rowpos": 147
    },
    {
      "ZID": 76,
      "SID": 792,
      "STID": 111,
      "Sportart": 34,
      "Streckenname": "Silberbach Loipe",
      "Laenge": 2300,
      "TC": 24,
      "HD": 24,
      "Schwierigkeitsgrad": 37,
      "LL_Technik": 40,
      "s_cmp": "silberbach loipe",
      "kats": [1],
      "trackstatus": 1,
      "rowpos": 148
    },
    {
      "ZID": 42,
      "SID": 675,
      "STID": 101,
      "Sportart": 34,
      "Streckenname": "Skating Loipe",
      "Laenge": 3900,
      "TC": 62,
      "HD": 32,
      "Schwierigkeitsgrad": 38,
      "LL_Technik": 42,
      "s_cmp": "skating loipe",
      "kats": [],
      "trackstatus": 1,
      "rowpos": 149
    },
    {
      "ZID": 70,
      "SID": 862,
      "STID": 177,
      "Sportart": 34,
      "Streckenname": "Skating Thurnerspur",
      "Laenge": 7500,
      "TC": 195,
      "HD": 82,
      "Schwierigkeitsgrad": 38,
      "LL_Technik": 42,
      "s_cmp": "skating thurnerspur",
      "kats": [],
      "trackstatus": 0,
      "rowpos": 150
    },
    {
      "ZID": 70,
      "SID": 771,
      "STID": 182,
      "Sportart": 34,
      "Streckenname": "Skatingloipe",
      "Laenge": 1600,
      "TC": 23,
      "HD": 14,
      "Schwierigkeitsgrad": 37,
      "LL_Technik": 42,
      "s_cmp": "skatingloipe",
      "kats": [],
      "trackstatus": 0,
      "rowpos": 151
    },
    {
      "ZID": 178,
      "SID": 765,
      "STID": 193,
      "Sportart": 34,
      "Streckenname": "Skatingloipe",
      "Laenge": 7200,
      "TC": 102,
      "HD": 29,
      "Schwierigkeitsgrad": 38,
      "LL_Technik": 42,
      "s_cmp": "skatingloipe",
      "kats": [],
      "trackstatus": 1,
      "rowpos": 152
    },
    {
      "ZID": 68,
      "SID": 741,
      "STID": 131,
      "Sportart": 34,
      "Streckenname": "Skiwanderweg",
      "Laenge": 20000,
      "TC": 502,
      "HD": 177,
      "Schwierigkeitsgrad": 39,
      "LL_Technik": 41,
      "s_cmp": "skiwanderweg",
      "kats": [3],
      "trackstatus": 1,
      "rowpos": 153
    },
    {
      "ZID": 75,
      "SID": 780,
      "STID": 164,
      "Sportart": 34,
      "Streckenname": "Sonnenloipe",
      "Laenge": 5000,
      "TC": 75,
      "HD": 25,
      "Schwierigkeitsgrad": 38,
      "LL_Technik": 40,
      "s_cmp": "sonnenloipe",
      "kats": [],
      "trackstatus": 1,
      "rowpos": 154
    },
    {
      "ZID": 42,
      "SID": 672,
      "STID": 101,
      "Sportart": 34,
      "Streckenname": "Sparkassen Nacht Loipe",
      "Laenge": 1900,
      "TC": 31,
      "HD": 20,
      "Schwierigkeitsgrad": 37,
      "LL_Technik": 40,
      "s_cmp": "sparkassen nacht loipe",
      "kats": [6],
      "trackstatus": 1,
      "rowpos": 155
    },
    {
      "ZID": 76,
      "SID": 793,
      "STID": 110,
      "Sportart": 34,
      "Streckenname": "St. Antoni - Spur",
      "Laenge": 7000,
      "TC": 131,
      "HD": 88,
      "Schwierigkeitsgrad": 38,
      "LL_Technik": 40,
      "s_cmp": "st. antoni - spur",
      "kats": [2],
      "trackstatus": 1,
      "rowpos": 156
    },
    {
      "ZID": 178,
      "SID": 1060,
      "STID": 193,
      "Sportart": 34,
      "Streckenname": "Stadionrunde",
      "Laenge": 400,
      "TC": 0,
      "HD": 0,
      "Schwierigkeitsgrad": 37,
      "LL_Technik": 40,
      "s_cmp": "stadionrunde",
      "kats": [],
      "trackstatus": 1,
      "rowpos": 157
    },
    {
      "ZID": 178,
      "SID": 766,
      "STID": 193,
      "Sportart": 34,
      "Streckenname": "Staudenloipe",
      "Laenge": 14500,
      "TC": 256,
      "HD": 114,
      "Schwierigkeitsgrad": 39,
      "LL_Technik": 41,
      "s_cmp": "staudenloipe",
      "kats": [],
      "trackstatus": 1,
      "rowpos": 158
    },
    {
      "ZID": 43,
      "SID": 708,
      "STID": 107,
      "Sportart": 34,
      "Streckenname": "Steffi Böhler Loipe 1",
      "Laenge": 2000,
      "TC": 14,
      "HD": 14,
      "Schwierigkeitsgrad": 37,
      "LL_Technik": 40,
      "s_cmp": "steffi bohler loipe 1",
      "kats": [],
      "trackstatus": 1,
      "rowpos": 159
    },
    {
      "ZID": 43,
      "SID": 709,
      "STID": 107,
      "Sportart": 34,
      "Streckenname": "Steffi Böhler Loipe 2",
      "Laenge": 2200,
      "TC": 41,
      "HD": 38,
      "Schwierigkeitsgrad": 38,
      "LL_Technik": 41,
      "s_cmp": "steffi bohler loipe 2",
      "kats": [],
      "trackstatus": 1,
      "rowpos": 160
    },
    {
      "ZID": 43,
      "SID": 710,
      "STID": 107,
      "Sportart": 34,
      "Streckenname": "Steffi Böhler Loipe 3",
      "Laenge": 7600,
      "TC": 157,
      "HD": 85,
      "Schwierigkeitsgrad": 39,
      "LL_Technik": 41,
      "s_cmp": "steffi bohler loipe 3",
      "kats": [5],
      "trackstatus": 1,
      "rowpos": 161
    },
    {
      "ZID": 43,
      "SID": 711,
      "STID": 107,
      "Sportart": 34,
      "Streckenname": "Steffi Böhler Loipe 4",
      "Laenge": 2400,
      "TC": 45,
      "HD": 40,
      "Schwierigkeitsgrad": 38,
      "LL_Technik": 41,
      "s_cmp": "steffi bohler loipe 4",
      "kats": [],
      "trackstatus": 1,
      "rowpos": 162
    },
    {
      "ZID": 174,
      "SID": 797,
      "STID": 782,
      "Sportart": 34,
      "Streckenname": "Stübenbachloipe",
      "Laenge": 3700,
      "TC": 79,
      "HD": 50,
      "Schwierigkeitsgrad": 37,
      "LL_Technik": 40,
      "s_cmp": "stubenbachloipe",
      "kats": [],
      "trackstatus": 0,
      "rowpos": 163
    },
    {
      "ZID": 60,
      "SID": 723,
      "STID": 785,
      "Sportart": 34,
      "Streckenname": "Stübenwasenspur",
      "Laenge": 19283,
      "TC": 533,
      "HD": 273,
      "Schwierigkeitsgrad": 39,
      "LL_Technik": 40,
      "s_cmp": "stubenwasenspur",
      "kats": [3],
      "trackstatus": 1,
      "rowpos": 164
    },
    {
      "ZID": 127,
      "SID": 1073,
      "STID": 116,
      "Sportart": 34,
      "Streckenname": "Tannenbodenloipe",
      "Laenge": 1200,
      "TC": 27,
      "HD": 20,
      "Schwierigkeitsgrad": 37,
      "LL_Technik": 40,
      "s_cmp": "tannenbodenloipe",
      "kats": [],
      "trackstatus": 0,
      "rowpos": 165
    },
    {
      "ZID": 17,
      "SID": 655,
      "STID": 120,
      "Sportart": 34,
      "Streckenname": "Taubenmoos Loipe",
      "Laenge": 2400,
      "TC": 43,
      "HD": 32,
      "Schwierigkeitsgrad": 37,
      "LL_Technik": 41,
      "s_cmp": "taubenmoos loipe",
      "kats": [],
      "trackstatus": 1,
      "rowpos": 166
    },
    {
      "ZID": 70,
      "SID": 858,
      "STID": 177,
      "Sportart": 34,
      "Streckenname": "Thurnerspur 1",
      "Laenge": 8200,
      "TC": 198,
      "HD": 78,
      "Schwierigkeitsgrad": 38,
      "LL_Technik": 41,
      "s_cmp": "thurnerspur 1",
      "kats": [],
      "trackstatus": 0,
      "rowpos": 167
    },
    {
      "ZID": 70,
      "SID": 859,
      "STID": 177,
      "Sportart": 34,
      "Streckenname": "Thurnerspur 2",
      "Laenge": 10000,
      "TC": 247,
      "HD": 117,
      "Schwierigkeitsgrad": 38,
      "LL_Technik": 41,
      "s_cmp": "thurnerspur 2",
      "kats": [],
      "trackstatus": 1,
      "rowpos": 168
    },
    {
      "ZID": 70,
      "SID": 860,
      "STID": 177,
      "Sportart": 34,
      "Streckenname": "Thurnerspur 3",
      "Laenge": 12000,
      "TC": 302,
      "HD": 143,
      "Schwierigkeitsgrad": 38,
      "LL_Technik": 41,
      "s_cmp": "thurnerspur 3",
      "kats": [],
      "trackstatus": 0,
      "rowpos": 169
    },
    {
      "ZID": 70,
      "SID": 861,
      "STID": 177,
      "Sportart": 34,
      "Streckenname": "Thurnerspur 4",
      "Laenge": 15000,
      "TC": 365,
      "HD": 153,
      "Schwierigkeitsgrad": 39,
      "LL_Technik": 41,
      "s_cmp": "thurnerspur 4",
      "kats": [3],
      "trackstatus": 1,
      "rowpos": 170
    },
    {
      "ZID": 41,
      "SID": 707,
      "STID": 129,
      "Sportart": 34,
      "Streckenname": "Tonispur",
      "Laenge": 4500,
      "TC": 114,
      "HD": 50,
      "Schwierigkeitsgrad": 39,
      "LL_Technik": 40,
      "s_cmp": "tonispur",
      "kats": [],
      "trackstatus": 1,
      "rowpos": 171
    },
    {
      "ZID": 17,
      "SID": 654,
      "STID": 120,
      "Sportart": 34,
      "Streckenname": "Trainings Loipe",
      "Laenge": 500,
      "TC": 8,
      "HD": 8,
      "Schwierigkeitsgrad": 37,
      "LL_Technik": 40,
      "s_cmp": "trainings loipe",
      "kats": [],
      "trackstatus": 1,
      "rowpos": 172
    },
    {
      "ZID": 75,
      "SID": 781,
      "STID": 172,
      "Sportart": 34,
      "Streckenname": "Trainingsloipe",
      "Laenge": 1600,
      "TC": 24,
      "HD": 12,
      "Schwierigkeitsgrad": 38,
      "LL_Technik": 41,
      "s_cmp": "trainingsloipe",
      "kats": [],
      "trackstatus": 1,
      "rowpos": 173
    },
    {
      "ZID": 175,
      "SID": 668,
      "STID": 187,
      "Sportart": 34,
      "Streckenname": "Trimm Strecke",
      "Laenge": 5900,
      "TC": 203,
      "HD": 71,
      "Schwierigkeitsgrad": 38,
      "LL_Technik": 40,
      "s_cmp": "trimm strecke",
      "kats": [],
      "trackstatus": 1,
      "rowpos": 174
    },
    {
      "ZID": 70,
      "SID": 770,
      "STID": 182,
      "Sportart": 34,
      "Streckenname": "Übungsloipe",
      "Laenge": 1600,
      "TC": 23,
      "HD": 14,
      "Schwierigkeitsgrad": 37,
      "LL_Technik": 41,
      "s_cmp": "ubungsloipe",
      "kats": [1],
      "trackstatus": 0,
      "rowpos": 175
    },
    {
      "ZID": 179,
      "SID": 1061,
      "STID": 190,
      "Sportart": 34,
      "Streckenname": "Übungsrunde",
      "Laenge": 900,
      "TC": "",
      "HD": "",
      "Schwierigkeitsgrad": 37,
      "LL_Technik": 41,
      "s_cmp": "ubungsrunde",
      "kats": [1],
      "trackstatus": 1,
      "rowpos": 176
    },
    {
      "ZID": 60,
      "SID": 12047,
      "STID": 788,
      "Sportart": 34,
      "Streckenname": "Übungsstrecke",
      "Laenge": 765,
      "TC": 16,
      "HD": 10,
      "Schwierigkeitsgrad": 37,
      "LL_Technik": 40,
      "s_cmp": "ubungsstrecke",
      "kats": [1],
      "trackstatus": 1,
      "rowpos": 177
    },
    {
      "ZID": 137,
      "SID": 712,
      "STID": 147,
      "Sportart": 34,
      "Streckenname": "Urseespur",
      "Laenge": 3000,
      "TC": 30,
      "HD": 26,
      "Schwierigkeitsgrad": 37,
      "LL_Technik": 41,
      "s_cmp": "urseespur",
      "kats": [],
      "trackstatus": 1,
      "rowpos": 178
    },
    {
      "ZID": 70,
      "SID": 774,
      "STID": 182,
      "Sportart": 34,
      "Streckenname": "Verbindung Thurner Spur",
      "Laenge": 5100,
      "TC": 203,
      "HD": 126,
      "Schwierigkeitsgrad": 39,
      "LL_Technik": 41,
      "s_cmp": "verbindung thurner spur",
      "kats": [],
      "trackstatus": 1,
      "rowpos": 179
    },
    {
      "ZID": 60,
      "SID": 12049,
      "STID": 787,
      "Sportart": 34,
      "Streckenname": "Verbindung zur Haldenspur",
      "Laenge": 1020,
      "TC": 7,
      "HD": 33,
      "Schwierigkeitsgrad": 40,
      "LL_Technik": 40,
      "s_cmp": "verbindung zur haldenspur",
      "kats": [],
      "trackstatus": 1,
      "rowpos": 180
    },
    {
      "ZID": 117,
      "SID": 684,
      "STID": 138,
      "Sportart": 34,
      "Streckenname": "Verbindungsloipe",
      "Laenge": 2900,
      "TC": 27,
      "HD": 140,
      "Schwierigkeitsgrad": 39,
      "LL_Technik": 40,
      "s_cmp": "verbindungsloipe",
      "kats": [],
      "trackstatus": 1,
      "rowpos": 181
    },
    {
      "ZID": 143,
      "SID": 3026,
      "STID": 798,
      "Sportart": 34,
      "Streckenname": "Verbindungsloipe nach Wolterdingen",
      "Laenge": 2461,
      "TC": "",
      "HD": "",
      "Schwierigkeitsgrad": 40,
      "LL_Technik": 41,
      "s_cmp": "verbindungsloipe nach wolterdingen",
      "kats": [],
      "trackstatus": 1,
      "rowpos": 182
    },
    {
      "ZID": 177,
      "SID": 755,
      "STID": 189,
      "Sportart": 34,
      "Streckenname": "Weissenbachloipe",
      "Laenge": 6000,
      "TC": 164,
      "HD": 106,
      "Schwierigkeitsgrad": 39,
      "LL_Technik": 41,
      "s_cmp": "weissenbachloipe",
      "kats": [],
      "trackstatus": 1,
      "rowpos": 183
    },
    {
      "ZID": 176,
      "SID": 750,
      "STID": 194,
      "Sportart": 34,
      "Streckenname": "Weltcup - Loipe",
      "Laenge": 2500,
      "TC": 78,
      "HD": 39,
      "Schwierigkeitsgrad": 39,
      "LL_Technik": 40,
      "s_cmp": "weltcup - loipe",
      "kats": [5, 7],
      "trackstatus": 1,
      "rowpos": 184
    },
    {
      "ZID": 39,
      "SID": 696,
      "STID": 162,
      "Sportart": 34,
      "Streckenname": "Windeck - Loipe",
      "Laenge": 5200,
      "TC": 125,
      "HD": 100,
      "Schwierigkeitsgrad": 39,
      "LL_Technik": 40,
      "s_cmp": "windeck - loipe",
      "kats": [],
      "trackstatus": 1,
      "rowpos": 185
    },
    {
      "ZID": 20,
      "SID": 1064,
      "STID": 167,
      "Sportart": 34,
      "Streckenname": "Wirbstein - Loipe",
      "Laenge": 5100,
      "TC": 128,
      "HD": 89,
      "Schwierigkeitsgrad": 38,
      "LL_Technik": 41,
      "s_cmp": "wirbstein - loipe",
      "kats": [],
      "trackstatus": 1,
      "rowpos": 186
    },
    {
      "ZID": 39,
      "SID": 690,
      "STID": 162,
      "Sportart": 34,
      "Streckenname": "Zartenbach - Loipe",
      "Laenge": 1900,
      "TC": 12,
      "HD": 7,
      "Schwierigkeitsgrad": 37,
      "LL_Technik": 40,
      "s_cmp": "zartenbach - loipe",
      "kats": [],
      "trackstatus": 1,
      "rowpos": 187
    }
  ],
  "Strecken_Index": {
    "652": 39,
    "653": 74,
    "654": 171,
    "655": 165,
    "656": 122,
    "657": 60,
    "658": 92,
    "659": 91,
    "660": 111,
    "661": 40,
    "662": 70,
    "663": 69,
    "664": 62,
    "665": 75,
    "666": 106,
    "667": 115,
    "668": 173,
    "669": 127,
    "670": 44,
    "671": 139,
    "672": 154,
    "673": 19,
    "674": 100,
    "675": 148,
    "676": 27,
    "677": 110,
    "678": 81,
    "679": 83,
    "680": 46,
    "681": 59,
    "684": 180,
    "685": 1,
    "686": 133,
    "687": 132,
    "688": 145,
    "689": 68,
    "690": 186,
    "691": 126,
    "692": 6,
    "693": 48,
    "694": 42,
    "695": 109,
    "696": 184,
    "697": 29,
    "698": 66,
    "700": 93,
    "701": 143,
    "702": 85,
    "703": 22,
    "704": 84,
    "705": 45,
    "706": 117,
    "707": 170,
    "708": 158,
    "709": 159,
    "710": 160,
    "711": 161,
    "712": 177,
    "713": 103,
    "714": 131,
    "715": 67,
    "716": 121,
    "717": 8,
    "718": 53,
    "719": 24,
    "720": 95,
    "721": 107,
    "722": 140,
    "723": 163,
    "724": 55,
    "725": 56,
    "726": 9,
    "727": 21,
    "728": 20,
    "729": 7,
    "730": 14,
    "731": 146,
    "732": 10,
    "733": 12,
    "734": 11,
    "735": 137,
    "736": 128,
    "737": 41,
    "738": 43,
    "739": 54,
    "740": 23,
    "741": 152,
    "742": 97,
    "743": 141,
    "744": 142,
    "745": 94,
    "746": 113,
    "747": 98,
    "749": 90,
    "750": 183,
    "752": 135,
    "753": 138,
    "754": 28,
    "755": 182,
    "756": 130,
    "757": 144,
    "758": 123,
    "759": 102,
    "760": 101,
    "761": 86,
    "762": 82,
    "763": 96,
    "764": 71,
    "765": 151,
    "766": 157,
    "767": 120,
    "768": 119,
    "769": 17,
    "770": 174,
    "771": 150,
    "772": 61,
    "773": 80,
    "774": 178,
    "775": 72,
    "776": 73,
    "777": 116,
    "778": 99,
    "779": 136,
    "780": 153,
    "781": 172,
    "782": 134,
    "783": 64,
    "784": 65,
    "785": 58,
    "786": 63,
    "787": 89,
    "788": 78,
    "789": 49,
    "790": 118,
    "791": 124,
    "792": 147,
    "793": 155,
    "794": 50,
    "796": 77,
    "797": 162,
    "798": 87,
    "799": 88,
    "800": 79,
    "801": 51,
    "802": 52,
    "858": 166,
    "859": 167,
    "860": 168,
    "861": 169,
    "862": 149,
    "863": 105,
    "1055": 13,
    "1056": 129,
    "1060": 156,
    "1061": 175,
    "1062": 112,
    "1063": 76,
    "1064": 185,
    "1065": 114,
    "1066": 104,
    "1067": 125,
    "1068": 108,
    "1069": 26,
    "1070": 25,
    "1071": 15,
    "1072": 18,
    "1073": 164,
    "1074": 47,
    "1075": 2,
    "1076": 4,
    "1077": 5,
    "2000": 30,
    "2001": 31,
    "2002": 32,
    "2003": 33,
    "2004": 34,
    "2005": 35,
    "2006": 36,
    "2007": 37,
    "2008": 38,
    "3026": 181,
    "3027": 16,
    "12045": 57,
    "12047": 176,
    "12049": 179,
    "12208": 0,
    "12210": 3
  },
  "Strecken_ST_Index": {
    "100": [674],
    "101": [673, 676, 678, 677, 675, 672],
    "102": [794],
    "104": [727],
    "105": [733],
    "106": [698, 702, 701],
    "107": [708, 709, 710, 711],
    "108": [732, 734],
    "109": [700],
    "110": [793],
    "111": [792],
    "112": [762],
    "113": [726, 728],
    "114": [1062],
    "115": [1074],
    "116": [1073],
    "117": [744],
    "118": [717, 718, 720],
    "119": [757],
    "120": [661, 657, 659, 660, 656, 655, 654],
    "121": [719],
    "122": [730, 731],
    "123": [739],
    "124": [721],
    "125": [658],
    "126": [653],
    "127": [729],
    "128": [758],
    "129": [707],
    "130": [737, 735],
    "131": [736, 743, 741],
    "132": [763, 742],
    "133": [703, 705, 706],
    "134": [704],
    "135": [740],
    "136": [761, 760, 759],
    "137": [681],
    "138": [684],
    "139": [738],
    "140": [2008],
    "141": [716],
    "143": [680],
    "144": [679],
    "145": [685, 687, 686],
    "147": [712],
    "151": [713],
    "152": [2006],
    "153": [694, 693, 691],
    "154": [688],
    "156": [715],
    "157": [714],
    "158": [778],
    "159": [692],
    "160": [689],
    "161": [2005],
    "162": [697, 695, 696, 690],
    "163": [789],
    "164": [788, 780],
    "165": [2004],
    "167": [1063, 1065, 1064],
    "168": [782],
    "169": [662],
    "170": [663],
    "171": [783, 784, 777, 790, 791],
    "172": [781],
    "173": [1066, 1068, 1067],
    "174": [785],
    "175": [664],
    "176": [786],
    "177": [863, 862, 858, 859, 860, 861],
    "178": [787, 779],
    "179": [665],
    "180": [2003],
    "181": [2002],
    "182": [772, 773, 771, 770, 774],
    "183": [666],
    "184": [775, 776],
    "185": [1055, 1056],
    "186": [753],
    "187": [2001, 670, 667, 669, 668],
    "188": [752],
    "189": [754, 756, 755],
    "190": [801, 802, 1061],
    "191": [671],
    "192": [769],
    "193": [764, 765, 1060, 766],
    "194": [745, 747, 746, 750],
    "195": [768, 767],
    "196": [1070, 1069],
    "197": [1071, 1072],
    "782": [796, 800, 798, 799, 797],
    "783": [2007],
    "784": [722],
    "785": [723],
    "786": [12208, 1075, 12210, 1076, 1077],
    "787": [12049],
    "788": [12047],
    "789": [724, 725, 12045],
    "798": [3026],
    "799": [3027],
    "813": [2000, 652, 749]
  }
}
